lineq/__init__.py
lineq/lineq.py
lineq-1.5.7.dist-info/LICENSE
lineq-1.5.7.dist-info/METADATA
lineq-1.5.7.dist-info/WHEEL
lineq-1.5.7.dist-info/top_level.txt
lineq-1.5.7.dist-info/RECORD
