Metadata-Version: 2.1
Name: lineq
Version: 1.5.7
Summary: This module returns the equation of the linear fitted curve!
Author: Amirreza Soltani
Author-email: charleswestmorelandPB1@gmail.com
Keywords: python,curve fitting,equation
Classifier: Programming Language :: Python :: 3
Classifier: License :: OSI Approved :: MIT License
Classifier: Operating System :: Unix
Classifier: Operating System :: MacOS :: MacOS X
Classifier: Operating System :: Microsoft :: Windows
Requires-Python: >=3.6
License-File: LICENSE
Requires-Dist: numpy
